mddj/__init__.py
mddj/__main__.py
mddj/_compat.py
mddj/_toml_path.py
mddj/_types.py
mddj/config.py
mddj/discovery.py
mddj/readers.py
mddj/writers.py
mddj/cli/__init__.py
mddj/cli/state.py
mddj/cli/read/__init__.py
mddj/cli/read/requires_python.py
mddj/cli/read/version.py
mddj/cli/read/tox/__init__.py
mddj/cli/read/tox/list_versions.py
mddj/cli/read/tox/min_version.py
mddj/cli/self/__init__.py
mddj/cli/self/version.py
mddj/cli/write/__init__.py
mddj/cli/write/version.py
mddj-0.3.0.dist-info/licenses/LICENSE.txt
mddj-0.3.0.dist-info/METADATA
mddj-0.3.0.dist-info/WHEEL
mddj-0.3.0.dist-info/entry_points.txt
mddj-0.3.0.dist-info/top_level.txt
mddj-0.3.0.dist-info/RECORD
