Metadata-Version: 2.4
Name: mddj
Version: 0.3.0
Summary: A CLI for extracting python metadata from packages
Author-email: Stephen Rosen <sirosen@globus.org>
License: MIT
Project-URL: source, https://github.com/sirosen/mddj
Project-URL: changelog, https://github.com/sirosen/mddj/blob/main/CHANGELOG.md
Classifier: Development Status :: 3 - Alpha
Classifier: Programming Language :: Python
Classifier: Programming Language :: Python :: 3.10
Classifier: Programming Language :: Python :: 3.11
Classifier: Programming Language :: Python :: 3.12
Classifier: Programming Language :: Python :: 3.13
Classifier: Programming Language :: Python :: 3.14
Classifier: Programming Language :: Python :: Implementation :: CPython
Classifier: Programming Language :: Python :: Implementation :: PyPy
Requires-Python: >=3.10
License-File: LICENSE.txt
Requires-Dist: wheel
Requires-Dist: packaging
Requires-Dist: build>=1.2.2
Requires-Dist: pyproject_hooks>1
Requires-Dist: click>=8.2.0
Requires-Dist: tomlkit>=0.13.2
Requires-Dist: typing_extensions; python_version < "3.13"
Dynamic: license-file
